typer_ui/__init__.py
typer_ui/command_executor.py
typer_ui/introspector.py
typer_ui/main.py
typer_ui/ui_components.py
typer_ui-0.1.2.dist-info/licenses/LICENSE
typer_ui-0.1.2.dist-info/METADATA
typer_ui-0.1.2.dist-info/WHEEL
typer_ui-0.1.2.dist-info/top_level.txt
typer_ui-0.1.2.dist-info/RECORD
