Metadata-Version: 2.4
Name: typer-ui
Version: 0.1.2
Summary: A UI package for Typer CLI apps.
Author: Amit Baswa
License: MIT
Requires-Python: >=3.7
License-File: LICENSE
Requires-Dist: typer
Requires-Dist: pydantic>=2.0.0
Requires-Dist: nicegui
Provides-Extra: test
Requires-Dist: pytest>=7.0.0; extra == "test"
Requires-Dist: pytest-asyncio; extra == "test"
Requires-Dist: pytest-cov; extra == "test"
Requires-Dist: pytest-mock; extra == "test"
Requires-Dist: tox; extra == "test"
Requires-Dist: faker; extra == "test"
Dynamic: license-file
